{
    "1": {
        "ErrorName":"TestError",
        "ErrorID": "1",
        "ErrorPossibleCause": "(TestErrorCause)",
        "ErrorDescription": "TestErrorDesc",
        "ErrorTitle": "TestErrorTitle"
    },
    "-40": {
        "ErrorName":"DisabledCommand",
        "ErrorID": "-40",
        "ErrorPossibleCause": "PermissionMissing",
        "ErrorDescription": "This command is disabled, Please enable it first before using.",
        "ErrorTitle": "Disabled Command!"
    },
    "-41": {
        "ErrorName":"RestrictedCommand",
        "ErrorID": "-41",
        "ErrorPossibleCause": "PermissionMissing",
        "ErrorDescription": "This command is restricted for authorized users only.",
        "ErrorTitle": "Restricted Command!"
    },
    "namiyen": {
        "ErrorName":"haha an error",
        "ErrorID": "namiyen",
        "ErrorPossibleCause": "SkillIssueCode",
        "ErrorDescription": "?",
        "ErrorTitle": "haha an error"
    }
}